CHANGES.rst
COPYING.txt
MANIFEST.in
README.rst
setup.py
quarry/__init__.py
quarry.egg-info/PKG-INFO
quarry.egg-info/SOURCES.txt
quarry.egg-info/dependency_links.txt
quarry.egg-info/requires.txt
quarry.egg-info/top_level.txt
quarry/data/__init__.py
quarry/data/data_packs.py
quarry/data/packets.py
quarry/data/data_packs/0753_1.16.3.nbt
quarry/data/data_packs/0754_1.16.4.nbt
quarry/data/data_packs/0755_1.17.nbt
quarry/data/data_packs/0756_1.17.1.nbt
quarry/data/data_packs/0757_1.18.nbt
quarry/data/data_packs/0758_1.18.2.nbt
quarry/data/data_packs/0759_1.19.nbt
quarry/data/data_packs/0760_1.19.1.nbt
quarry/data/keys/yggdrasil_session_pubkey.der
quarry/data/packets/0004_1.7.5.csv
quarry/data/packets/0005_1.7.10.csv
quarry/data/packets/0047_1.8.8.csv
quarry/data/packets/0107_1.9.csv
quarry/data/packets/0108_1.9.1.csv
quarry/data/packets/0109_1.9.2.csv
quarry/data/packets/0110_1.9.4.csv
quarry/data/packets/0210_1.10.csv
quarry/data/packets/0315_1.11.csv
quarry/data/packets/0316_1.11.2.csv
quarry/data/packets/0335_1.12.csv
quarry/data/packets/0338_1.12.1.csv
quarry/data/packets/0340_1.12.2.csv
quarry/data/packets/0393_1.13.csv
quarry/data/packets/0401_1.13.1.csv
quarry/data/packets/0404_1.13.2.csv
quarry/data/packets/0477_1.14.csv
quarry/data/packets/0480_1.14.1.csv
quarry/data/packets/0485_1.14.2.csv
quarry/data/packets/0490_1.14.3.csv
quarry/data/packets/0498_1.14.4.csv
quarry/data/packets/0573_1.15.csv
quarry/data/packets/0575_1.15.1.csv
quarry/data/packets/0578_1.15.2.csv
quarry/data/packets/0736_1.16.1.csv
quarry/data/packets/0751_1.16.2.csv
quarry/data/packets/0753_1.16.3.csv
quarry/data/packets/0754_1.16.4.csv
quarry/data/packets/0755_1.17.csv
quarry/data/packets/0756_1.17.1.csv
quarry/data/packets/0757_1.18.csv
quarry/data/packets/0758_1.18.2.csv
quarry/data/packets/0759_1.19.csv
quarry/data/packets/0760_1.19.1.csv
quarry/net/__init__.py
quarry/net/auth.py
quarry/net/client.py
quarry/net/crypto.py
quarry/net/http.py
quarry/net/protocol.py
quarry/net/proxy.py
quarry/net/server.py
quarry/net/ticker.py
quarry/types/__init__.py
quarry/types/chat.py
quarry/types/chunk.py
quarry/types/nbt.py
quarry/types/registry.py
