Metadata-Version: 2.1
Name: quarry
Version: 1.9.4
Summary: Minecraft protocol library
Home-page: https://github.com/barneygale/quarry
Author: Barney Gale
Author-email: barney@barneygale.co.uk
License: MIT
License-File: COPYING.txt
